LICENSE
MANIFEST.in
README
README.rst
setup.cfg
setup.py
src/clik/__init__.py
src/clik/app.py
src/clik/argparse.py
src/clik/command.py
src/clik/compat.py
src/clik/context.py
src/clik/magic.py
src/clik/util.py
src/clik.egg-info/PKG-INFO
src/clik.egg-info/SOURCES.txt
src/clik.egg-info/dependency_links.txt
src/clik.egg-info/not-zip-safe
src/clik.egg-info/top_level.txt